{
  "_note1": "KEEP THIS FILE! Check it into a version control system (VCS) like git.",
  "_note2": "ObjectBox manages crucial IDs for your object model. See docs for details.",
  "_note3": "If you have VCS merge conflicts, you must resolve them according to ObjectBox docs.",
  "entities": [
    {
      "id": "1:75691064871373534",
      "lastPropertyId": "4:8916581932999931584",
      "name": "PatrolEventModel",
      "properties": [
        {
          "id": "1:6984677465033183772",
          "name": "patrolEventId",
          "type": 6,
          "flags": 1
        },
        {
          "id": "2:8728213409163117172",
          "name": "tagId",
          "type": 6
        },
        {
          "id": "3:445448907958993337",
          "name": "eventDateTime",
          "type": 10
        },
        {
          "id": "4:8916581932999931584",
          "name": "unitId",
          "type": 6
        }
      ],
      "relations": []
    },
    {
      "id": "2:5027176135146991495",
      "lastPropertyId": "3:4328713346741113261",
      "name": "PanicAlertEventModel",
      "properties": [
        {
          "id": "1:6632438436881818630",
          "name": "panicAlertEventId",
          "type": 6,
          "flags": 1
        },
        {
          "id": "2:4757531137973359325",
          "name": "unitId",
          "type": 6
        },
        {
          "id": "3:4328713346741113261",
          "name": "eventDateTime",
          "type": 10
        }
      ],
      "relations": []
    },
    {
      "id": "3:2821305195249272947",
      "lastPropertyId": "2:3600672083111990031",
      "name": "UnitModel",
      "properties": [
        {
          "id": "1:810276591203446414",
          "name": "unitId",
          "type": 6,
          "flags": 1
        },
        {
          "id": "2:3600672083111990031",
          "name": "unitName",
          "type": 9
        }
      ],
      "relations": [
        {
          "id": "1:7009608560862662240",
          "name": "tagModelList",
          "targetId": "4:3263619209923188303"
        }
      ]
    },
    {
      "id": "4:3263619209923188303",
      "lastPropertyId": "4:5018721905925567127",
      "name": "TagModel",
      "properties": [
        {
          "id": "1:1880346535826512557",
          "name": "id",
          "type": 6,
          "flags": 1
        },
        {
          "id": "2:4151838864869919433",
          "name": "title",
          "type": 9
        },
        {
          "id": "3:5341133999396300665",
          "name": "type",
          "type": 9
        },
        {
          "id": "4:5018721905925567127",
          "name": "isActive",
          "type": 1
        }
      ],
      "relations": []
    }
  ],
  "lastEntityId": "4:3263619209923188303",
  "lastIndexId": "0:0",
  "lastRelationId": "1:7009608560862662240",
  "lastSequenceId": "0:0",
  "modelVersion": 5,
  "modelVersionParserMinimum": 5,
  "retiredEntityUids": [],
  "retiredIndexUids": [],
  "retiredPropertyUids": [],
  "retiredRelationUids": [],
  "version": 1
}